django_agent_runtime/__init__.py
django_agent_runtime/admin.py
django_agent_runtime/apps.py
django_agent_runtime/conf.py
django_agent_runtime/urls.py
django_agent_runtime/api/__init__.py
django_agent_runtime/api/permissions.py
django_agent_runtime/api/serializers.py
django_agent_runtime/api/views.py
django_agent_runtime/dynamic_tools/__init__.py
django_agent_runtime/dynamic_tools/executor.py
django_agent_runtime/dynamic_tools/generator.py
django_agent_runtime/dynamic_tools/loader.py
django_agent_runtime/dynamic_tools/scanner.py
django_agent_runtime/examples/__init__.py
django_agent_runtime/examples/langgraph_adapter.py
django_agent_runtime/examples/langgraph_tools.py
django_agent_runtime/examples/simple_chat.py
django_agent_runtime/examples/tool_agent.py
django_agent_runtime/management/__init__.py
django_agent_runtime/management/commands/__init__.py
django_agent_runtime/management/commands/clear_agent_data.py
django_agent_runtime/management/commands/runagent.py
django_agent_runtime/migrations/0001_initial.py
django_agent_runtime/migrations/0002_persistence_models.py
django_agent_runtime/migrations/0003_persistenceconversation_active_branch_id_and_more.py
django_agent_runtime/migrations/0004_add_anonymous_session_id.py
django_agent_runtime/migrations/0005_agentdefinition_agentknowledge_agenttool_and_more.py
django_agent_runtime/migrations/0006_step_execution_models.py
django_agent_runtime/migrations/0007_discoveredfunction_dynamictool_dynamictoolexecution.py
django_agent_runtime/migrations/0008_add_agent_revision.py
django_agent_runtime/migrations/0009_add_rag_fields.py
django_agent_runtime/migrations/0010_alter_agentdefinition_rag_config.py
django_agent_runtime/migrations/0011_add_subagent_invocation_fields.py
django_agent_runtime/migrations/0012_add_agent_system_models.py
django_agent_runtime/migrations/0013_add_sub_agent_tool.py
django_agent_runtime/migrations/0014_add_conversation_id_to_fact.py
django_agent_runtime/migrations/0015_add_agent_spec.py
django_agent_runtime-0.7.6.dist-info/licenses/LICENSE
django_agent_runtime-0.7.6.dist-info/METADATA
django_agent_runtime-0.7.6.dist-info/WHEEL
django_agent_runtime-0.7.6.dist-info/top_level.txt
django_agent_runtime-0.7.6.dist-info/RECORD
