Metadata-Version: 2.4
Name: django-agent-runtime
Version: 0.7.6
Summary: Production-grade AI agent runtime for Django - framework and model agnostic
Author: Chris Barry
License-Expression: MIT
Project-URL: Homepage, https://github.com/makemore/django-agent-runtime
Project-URL: Documentation, https://github.com/makemore/django-agent-runtime#readme
Project-URL: Repository, https://github.com/makemore/django-agent-runtime
Project-URL: Issues, https://github.com/makemore/django-agent-runtime/issues
Keywords: django,ai,agent,llm,runtime,async
Classifier: Development Status :: 3 - Alpha
Classifier: Environment :: Web Environment
Classifier: Framework :: Django
Classifier: Framework :: Django :: 4.2
Classifier: Framework :: Django :: 5.0
Classifier: Intended Audience :: Developers
Classifier: Operating System :: OS Independent
Classifier: Programming Language :: Python :: 3
Classifier: Programming Language :: Python :: 3.10
Classifier: Programming Language :: Python :: 3.11
Classifier: Programming Language :: Python :: 3.12
Classifier: Topic :: Software Development :: Libraries :: Python Modules
Requires-Python: >=3.10
License-File: LICENSE
Requires-Dist: Django>=4.2
Requires-Dist: djangorestframework>=3.14
Requires-Dist: agent-runtime-core>=0.4.0
Provides-Extra: redis
Requires-Dist: redis>=4.5.0; extra == "redis"
Provides-Extra: openai
Requires-Dist: openai>=1.0.0; extra == "openai"
Provides-Extra: anthropic
Requires-Dist: anthropic>=0.18.0; extra == "anthropic"
Provides-Extra: litellm
Requires-Dist: litellm>=1.0.0; extra == "litellm"
Provides-Extra: langfuse
Requires-Dist: langfuse>=2.0.0; extra == "langfuse"
Provides-Extra: framework
Requires-Dist: agent-runtime-framework>=0.1.0; extra == "framework"
Provides-Extra: pgvector
Requires-Dist: pgvector>=0.2.0; extra == "pgvector"
Requires-Dist: psycopg[binary]>=3.1.0; extra == "pgvector"
Provides-Extra: recommended
Requires-Dist: django-agent-runtime[framework,openai,redis]; extra == "recommended"
Provides-Extra: all
Requires-Dist: django-agent-runtime[anthropic,framework,langfuse,litellm,openai,pgvector,redis]; extra == "all"
Provides-Extra: dev
Requires-Dist: pytest>=7.0; extra == "dev"
Requires-Dist: pytest-django>=4.5; extra == "dev"
Requires-Dist: pytest-asyncio>=0.21; extra == "dev"
Requires-Dist: pytest-cov>=4.0; extra == "dev"
Requires-Dist: black>=23.0; extra == "dev"
Requires-Dist: ruff>=0.1.0; extra == "dev"
Requires-Dist: mypy>=1.0; extra == "dev"
Dynamic: license-file
